ec2_reaper/__init__.py
ec2_reaper/aws_lambda.py
ec2_reaper/cli.py
ec2_reaper/ec2_reaper.py
ec2_reaper-0.1.8.dist-info/DESCRIPTION.rst
ec2_reaper-0.1.8.dist-info/METADATA
ec2_reaper-0.1.8.dist-info/RECORD
ec2_reaper-0.1.8.dist-info/WHEEL
ec2_reaper-0.1.8.dist-info/entry_points.txt
ec2_reaper-0.1.8.dist-info/metadata.json
ec2_reaper-0.1.8.dist-info/top_level.txt
