Metadata-Version: 2.0
Name: ec2-reaper
Version: 0.1.8
Summary: CLI & module for terminating instances that match tag and age requirements.
Home-page: https://github.com/inhumantsar/python-ec2-reaper
Author: Shaun Martin
Author-email: shaun@samsite.ca
License: BSD license
Keywords: ec2-reaper
Platform: UNKNOWN
Classifier: Development Status :: 2 - Pre-Alpha
Classifier: Intended Audience :: Developers
Classifier: License :: OSI Approved :: BSD License
Classifier: Natural Language :: English
Classifier: Programming Language :: Python :: 2
Classifier: Programming Language :: Python :: 2.7
Classifier: Programming Language :: Python :: 3
Classifier: Programming Language :: Python :: 3.4
Classifier: Programming Language :: Python :: 3.5
Classifier: Programming Language :: Python :: 3.6
Requires-Dist: boto3 (==1.5.6)
Requires-Dist: pytz (==2017.3)
Requires-Dist: slacker (==0.9.60)
Requires-Dist: click (==6.7)
